{"test_cases": [{"name": "root -> zeros", "ok": true, "status": "OK"}, {"name": "root -> ones", "ok": true, "status": "OK"}, {"name": "root -> custom", "ok": true, "status": "OK"}, {"name": "root -> shape -> 0", "ok": true, "status": "OK"}, {"name": "root -> shape -> 1", "ok": true, "status": "OK"}, {"name": "root -> mean", "ok": true, "status": "OK"}, {"name": "root -> std", "ok": true, "status": "OK"}, {"name": "root -> min_val", "ok": true, "status": "OK"}, {"name": "root -> max_val", "ok": true, "status": "OK"}, {"name": "root -> x_0", "ok": true, "status": "OK"}, {"name": "root -> x_1", "ok": true, "status": "OK"}, {"name": "root -> x_0_0", "ok": true, "status": "OK"}, {"name": "root -> x_all_0", "ok": true, "status": "OK"}, {"name": "root -> x_and_10", "ok": true, "status": "OK"}, {"name": "root -> x_squared", "ok": true, "status": "OK"}, {"name": "root -> x_plus_y", "ok": true, "status": "OK"}, {"name": "root -> x_times_y", "ok": true, "status": "OK"}, {"name": "root -> x_divided_by_y", "ok": true, "status": "OK"}, {"name": "root -> x_mod_y", "ok": true, "status": "OK"}, {"name": "root -> x_exp", "ok": true, "status": "OK"}, {"name": "root -> x_log", "ok": true, "status": "OK"}, {"name": "root -> x_sin", "ok": true, "status": "OK"}, {"name": "root -> x_cos", "ok": true, "status": "OK"}, {"name": "root -> x_matmul_y", "ok": true, "status": "OK"}, {"name": "root -> x_greater_than_3", "ok": true, "status": "OK"}, {"name": "root -> x_greater_than_3_and_less_than_10", "ok": true, "status": "OK"}, {"name": "root -> x_greater_than_10_or_less_than_3", "ok": true, "status": "OK"}, {"name": "root -> x_not_equal_to_3", "ok": true, "status": "OK"}, {"name": "root -> x_vals_greater_than_3", "ok": true, "status": "OK"}, {"name": "root -> y_shallow", "ok": true, "status": "OK"}, {"name": "root -> x_shallow_victim", "ok": true, "status": "OK"}, {"name": "root -> y_deep", "ok": true, "status": "OK"}, {"name": "root -> x_cloned", "ok": true, "status": "OK"}, {"name": "root -> x_dtype", "ok": true, "status": "OK"}, {"name": "root -> x_double", "ok": true, "status": "OK"}, {"name": "root -> x_int", "ok": true, "status": "OK"}, {"name": "root -> x_float", "ok": true, "status": "OK"}, {"name": "root -> x_half", "ok": true, "status": "OK"}, {"name": "root -> x_torch", "ok": true, "status": "OK"}, {"name": "root -> x_sqrt_np", "ok": true, "status": "OK"}]}